{
  "pools": [
    {
      "rolls": 1,
      "entries": [
        {
          "type": "minecraft:item",
          "name": "minecraft:carrot_on_a_stick",
          "weight": 1,
          "functions": [
            {
              "function": "minecraft:set_components",
              "components": {
                "minecraft:item_model": "minecraft:breeze_rod",
                "minecraft:enchantment_glint_override": true,
                "minecraft:rarity": "epic",
                "minecraft:custom_data": {
                  "magicraft.item.wand": true,
                  "magicraft.item.wand.air": true
                },
                "minecraft:custom_name": {
                  "translate": "magicraft.translate.wand.air",
                  "fallback": "Air Wand",
                  "italic": false
                }
              }
            }
          ]
        }
      ]
    }
  ]
}